im_ndbsharded/__init__.py
im_ndbsharded-0.1.2.dist-info/DESCRIPTION.rst
im_ndbsharded-0.1.2.dist-info/METADATA
im_ndbsharded-0.1.2.dist-info/RECORD
im_ndbsharded-0.1.2.dist-info/WHEEL
im_ndbsharded-0.1.2.dist-info/metadata.json
im_ndbsharded-0.1.2.dist-info/top_level.txt
